{
  "episode": "Setting the Record Straight: I Was Forced to Respond",
  "posted_at": "2026-06-08",
  "snapshot_tag": "t5",
  "pulled_at": "2026-06-16T22:47:55.079896+00:00",
  "records": [
    {
      "platform": "youtube",
      "url": "https://www.youtube.com/watch?v=B9AEB8MOo1E",
      "id": "B9AEB8MOo1E",
      "title": "Setting the Record Straight: I Was Forced to Respond",
      "uploader": "Talking Downey",
      "upload_date": "20260608",
      "timestamp": 1780902014,
      "duration_s": 1620,
      "view_count": 336,
      "like_count": 16,
      "comment_count": 2,
      "repost_count": null,
      "description_excerpt": "After being publicly mentioned multiple times during recent meetings and political discussions involving Downey Councilmember Mario Trujillo, former Mayor Mario Guerra says enough is enough.\n\nIn this ",
      "label": "youtube"
    },
    {
      "platform": "tiktok",
      "url": "https://www.tiktok.com/@talkingdowney/video/7649093006326271245",
      "id": "7649093006326271245",
      "title": "Responding to your yapping, Downey! Big things are happening. This is...",
      "uploader": "talkingdowney",
      "upload_date": "20260608",
      "timestamp": 1780943252,
      "duration_s": 21,
      "view_count": 1278,
      "like_count": 25,
      "comment_count": 0,
      "repost_count": 1,
      "description_excerpt": "Responding to your yapping, Downey! Big things are happening. This is for you, especially since you mentioned me. Seems like a pattern now. #Downey #Community #LocalNews #Response",
      "label": "tiktok_1"
    },
    {
      "platform": "tiktok",
      "url": "https://www.tiktok.com/@talkingdowney/video/7646481393416965389",
      "id": "7646481393416965389",
      "title": "Politicians' promises often fall short. Real change needs honesty & e...",
      "uploader": "talkingdowney",
      "upload_date": "20260601",
      "timestamp": 1780335121,
      "duration_s": 83,
      "view_count": 1385,
      "like_count": 69,
      "comment_count": 0,
      "repost_count": 0,
      "description_excerpt": "Politicians' promises often fall short. Real change needs honesty & everyone stepping up. Let's demand better. #Politics #Honesty #Change #CivicDuty",
      "label": "tiktok_2"
    },
    {
      "platform": "tiktok",
      "url": "https://www.tiktok.com/@talkingdowney/video/7646457629224537357",
      "id": "7646457629224537357",
      "title": "Giving second chances: Even when probation objects, a judge can offer...",
      "uploader": "talkingdowney",
      "upload_date": "20260601",
      "timestamp": 1780329665,
      "duration_s": 38,
      "view_count": 383,
      "like_count": 4,
      "comment_count": 0,
      "repost_count": 0,
      "description_excerpt": "Giving second chances: Even when probation objects, a judge can offer a path to redemption. Programs, progress, and a new direction. #SecondChance #Redemption #JusticeReform #NewBeginnings",
      "label": "tiktok_3"
    },
    {
      "platform": "tiktok",
      "url": "https://www.tiktok.com/@talkingdowney/video/7646166793605647630",
      "id": "7646166793605647630",
      "title": "Bridging cultures: The secret weapon against tech's dark side and a p...",
      "uploader": "talkingdowney",
      "upload_date": "20260531",
      "timestamp": 1780261937,
      "duration_s": 38,
      "view_count": 292,
      "like_count": 2,
      "comment_count": 0,
      "repost_count": 0,
      "description_excerpt": "Bridging cultures: The secret weapon against tech's dark side and a pathway to global peace. Sister cities are just the start! #CulturalExchange #GlobalPeace #SisterCities #SocietalImprovement #Apprec",
      "label": "tiktok_4"
    },
    {
      "platform": "tiktok",
      "url": "https://www.tiktok.com/@talkingdowney/video/7646163844078783758",
      "id": "7646163844078783758",
      "title": "From civil law to prosecution, this attorney brings a unique blend of...",
      "uploader": "talkingdowney",
      "upload_date": "20260531",
      "timestamp": 1780261250,
      "duration_s": 39,
      "view_count": 267,
      "like_count": 2,
      "comment_count": 0,
      "repost_count": 0,
      "description_excerpt": "From civil law to prosecution, this attorney brings a unique blend of experience and empathy. Ready to tackle any assignment with hard work and pride. #LegalEagle #AttorneyLife #Lawyer #BehindTheScene",
      "label": "tiktok_5"
    }
  ]
}